reachable/VERSION.md
reachable/__init__.py
reachable/client.py
reachable/main.py
reachable/playwright_client.py
reachable/pool.py
reachable-0.9.1.dist-info/METADATA
reachable-0.9.1.dist-info/WHEEL
reachable-0.9.1.dist-info/licenses/LICENSE
reachable-0.9.1.dist-info/RECORD
