Metadata-Version: 2.4
Name: reachable
Version: 0.9.1
Summary: Check if a URL is reachable
Project-URL: Homepage, https://github.com/AlexMili/Reachable
Project-URL: Issues, https://github.com/AlexMili/Reachable/issues
Project-URL: Repository, https://github.com/AlexMili/Reachable
Project-URL: Documentation, https://github.com/AlexMili/Reachable
Author: Alex Mili
License: MIT License
License-File: LICENSE
Classifier: Intended Audience :: Developers
Classifier: License :: OSI Approved :: MIT License
Requires-Python: >=3.8
Requires-Dist: brotli
Requires-Dist: fake-useragent
Requires-Dist: httpx[http2]
Requires-Dist: tldextract
Requires-Dist: tqdm
Requires-Dist: zstandard
Provides-Extra: playwright
Requires-Dist: playwright; extra == 'playwright'
Provides-Extra: test
Requires-Dist: pytest; extra == 'test'
Requires-Dist: pytest-asyncio; extra == 'test'
Requires-Dist: pytest-cov; extra == 'test'
